PyRVC.cp37-win_amd64.pyd
rvctestb-1.7.0.dist-info/METADATA
rvctestb-1.7.0.dist-info/WHEEL
rvctestb-1.7.0.dist-info/top_level.txt
rvctestb-1.7.0.dist-info/RECORD
