Metadata-Version: 2.1
Name: rvctestb
Version: 1.7.0
Summary: Rvbust RVC X Camera Python SDK
Author: rvbust
Author-email: 
